showhype_lib/__init__.py
showhype_lib/service_callback.py
showhype_lib-0.1.0.dist-info/METADATA
showhype_lib-0.1.0.dist-info/WHEEL
showhype_lib-0.1.0.dist-info/top_level.txt
showhype_lib-0.1.0.dist-info/RECORD
